nonebot_plugin_gemini_vision/__init__.py
nonebot_plugin_gemini_vision/config.py
nonebot_plugin_gemini_vision/core.py
nonebot_plugin_gemini_vision-1.0.9.dist-info/licenses/LICENSE
nonebot_plugin_gemini_vision-1.0.9.dist-info/METADATA
nonebot_plugin_gemini_vision-1.0.9.dist-info/WHEEL
nonebot_plugin_gemini_vision-1.0.9.dist-info/top_level.txt
nonebot_plugin_gemini_vision-1.0.9.dist-info/RECORD
