Metadata-Version: 2.4
Name: nonebot-plugin-gemini-vision
Version: 1.0.9
Summary: 支持生成图片、编辑图片、理解图片的gemini插件
Author-email: X-Zero-L <zeroeeau@gmail.com>
Project-URL: Repository, https://github.com/X-Zero-L/nonebot-plugin-gemini-vision
Requires-Python: <3.13,>=3.10
License-File: LICENSE
Requires-Dist: httpx<1.0.0,>=0.27.0
Requires-Dist: nonebot2<3.0.0,>=2.4.2
Requires-Dist: nonebot-plugin-uninfo<1.0.0,>=0.7.0
Requires-Dist: nonebot-plugin-alconna<1.0.0,>=0.56.2
Requires-Dist: nonebot-plugin-session>=0.3.2
Requires-Dist: google-genai>=1.8.0
Requires-Dist: aiohttp>=3.11.14
Dynamic: license-file
